set_db_pdi
