Metadata-Version: 1.1
Name: pentaho-db-changer
Version: 0.0.3
Summary: Change dynamically Pentaho database connections from kjb, ktr and xml files
Home-page: https://github.com/kappius/pyheaderfile
Author: Diogo Munaro Vieira, Thiago Pereira Fernandes
Author-email: diogo.mvieira@gmail.com, thiago.fernandes210@gmail.com
License: Apache
Download-URL: https://github.com/kappius/pyheaderfile/archive/0.0.3.tar.gz
Keywords: pentaho,kettle,report,ktr,kjb,xml,txt
Platform: UNKNOWN
Classifier: Programming Language :: Python
Classifier: Programming Language :: Python :: 2
Classifier: Operating System :: OS Independent
Classifier: Topic :: Database
Classifier: Topic :: Office/Business
Classifier: Topic :: Software Development :: Libraries :: Python Modules
Classifier: Topic :: Utilities
